<?xml version="1.0" standalone="yes"?>
<BandingDataSet>
  <BandingData>
    <BandingColor>Super White</BandingColor>
    <BandingPrice>0.1</BandingPrice>
  </BandingData>
  <BandingData>
    <BandingColor>White</BandingColor>
    <BandingPrice>0.1</BandingPrice>
  </BandingData>
  <BandingData>
    <BandingColor>Nova White</BandingColor>
    <BandingPrice>0.1</BandingPrice>
  </BandingData>
  <BandingData>
    <BandingColor>White White</BandingColor>
    <BandingPrice>0.1</BandingPrice>
  </BandingData>
  <BandingData>
    <BandingColor>Sunset Grey</BandingColor>
    <BandingPrice>0.1</BandingPrice>
  </BandingData>
  <BandingData>
    <BandingColor>Canadian Grey</BandingColor>
    <BandingPrice>0.1</BandingPrice>
  </BandingData>
  <BandingData>
    <BandingColor>Black</BandingColor>
    <BandingPrice>0.1</BandingPrice>
  </BandingData>
  <BandingData>
    <BandingColor>Antique White</BandingColor>
    <BandingPrice>0.1</BandingPrice>
  </BandingData>
  <BandingData>
    <BandingColor>New England Almond</BandingColor>
    <BandingPrice>0.1</BandingPrice>
  </BandingData>
  <BandingData>
    <BandingColor>Classic Maple</BandingColor>
    <BandingPrice>0.1</BandingPrice>
  </BandingData>
  <BandingData>
    <BandingColor>Hardrock Maple</BandingColor>
    <BandingPrice>0.1</BandingPrice>
  </BandingData>
  <BandingData>
    <BandingColor>Pear</BandingColor>
    <BandingPrice>0.1</BandingPrice>
  </BandingData>
  <BandingData>
    <BandingColor>Chocolate Apple</BandingColor>
    <BandingPrice>0.1</BandingPrice>
  </BandingData>
  <BandingData>
    <BandingColor>Wild Apple</BandingColor>
    <BandingPrice>0.1</BandingPrice>
  </BandingData>
  <BandingData>
    <BandingColor>Wild Apple Rust</BandingColor>
    <BandingPrice>0.1</BandingPrice>
  </BandingData>
  <BandingData>
    <BandingColor>Alabama Cherry</BandingColor>
    <BandingPrice>0.1</BandingPrice>
  </BandingData>
  <BandingData>
    <BandingColor>Stainless</BandingColor>
    <BandingPrice>0.1</BandingPrice>
  </BandingData>
  <BandingData>
    <BandingColor>Navajo Red</BandingColor>
    <BandingPrice>0.1</BandingPrice>
  </BandingData>
  <BandingData>
    <BandingColor>(EW) Silva</BandingColor>
    <BandingPrice>0.1</BandingPrice>
  </BandingData>
  <BandingData>
    <BandingColor>(EW) Zahara</BandingColor>
    <BandingPrice>0.1</BandingPrice>
  </BandingData>
  <BandingData>
    <BandingColor>(EW) Ember</BandingColor>
    <BandingPrice>0.1</BandingPrice>
  </BandingData>
  <BandingData>
    <BandingColor>(EW) Skye</BandingColor>
    <BandingPrice>0.1</BandingPrice>
  </BandingData>
  <BandingData>
    <BandingColor>(EW) Dritwood</BandingColor>
    <BandingPrice>0.1</BandingPrice>
  </BandingData>
  <BandingData>
    <BandingColor>Veneer</BandingColor>
    <BandingPrice>0.1</BandingPrice>
  </BandingData>
</BandingDataSet>